xxhash_cffi/__init__.py
xxhash_cffi/_cffi.so
xxhash_cffi/cffi.py
xxhash_cffi-1.3.0.dist-info/LICENSE
xxhash_cffi-1.3.0.dist-info/METADATA
xxhash_cffi-1.3.0.dist-info/WHEEL
xxhash_cffi-1.3.0.dist-info/top_level.txt
xxhash_cffi-1.3.0.dist-info/RECORD
